metro_ticket_gate.v
module metro_ticket_gate (
    input  wire       clk,               // System clock
    input  wire       reset,             // Synchronous active-high reset
    input  wire       card_detected,     // High when a card is tapped
    input  wire       ticket_valid,      // High when card passes validation
    input  wire       passenger_crossed, // High when IR sensor detects crossing
    input  wire       timeout,           // High when open-gate timer expires
    input  wire       emergency,         // High for emergency (gate forced open)
    input  wire       maintenance,       // High to enter maintenance mode
    output reg        gate_open,         // High = gate barrier lifted
    output reg        alarm,             // High = audible/visual alert active
    output reg  [3:0] display,           // 4-bit encoded display code (see params)
    output wire [7:0] entry_count        // Running count of successful entries
);

//  State Encoding (parameter-based, one-hot friendly binary)

parameter [3:0]
    IDLE              = 4'd0,
    CARD_DETECTED     = 4'd1,
    VALIDATE          = 4'd2,
    OPEN_GATE         = 4'd3,
    WAIT_FOR_PASSENGER= 4'd4,
    CLOSE_GATE        = 4'd5,
    INVALID_TICKET    = 4'd6,
    EMERGENCY         = 4'd7,
    MAINTENANCE       = 4'd8;


//  Display Codes (4-bit values driven onto `display` output)
//  External decoder (7-seg or LED bar) maps these to text/icons

parameter [3:0]
    DISP_IDLE        = 4'h0,   // "--"  ready
    DISP_CARD        = 4'h1,   // "CD"  card detected
    DISP_VALIDATING  = 4'h2,   // "VA"  validating
    DISP_OPEN        = 4'h3,   // "GO"  gate open
    DISP_WAIT        = 4'h4,   // "PS"  please step through
    DISP_CLOSING     = 4'h5,   // "CL"  closing
    DISP_INVALID     = 4'h6,   // "ER"  error / invalid
    DISP_EMERGENCY   = 4'h7,   // "EM"  emergency
    DISP_MAINTENANCE = 4'h8;   // "MN"  maintenance

//  Internal Registers

reg [3:0] state;          // Current FSM state
reg [3:0] next_state;     // Next FSM state (combinational)
reg [7:0] entry_cnt_reg;  // Passenger entry counter
reg       count_en;       // Pulse: increment counter this cycle
reg [3:0] alarm_cnt;      // Counts down alarm duration

// Expose counter as output
assign entry_count = entry_cnt_reg;

//  BLOCK 1 — State Register (sequential)
//  Registers current state on every rising clock edge.
//  Emergency and Maintenance inputs are checked here for
//  immediate (priority) override of any ongoing state.

always @(posedge clk) begin
    if (reset) begin
        state <= IDLE;
    end
    else if (emergency) begin
        // Emergency overrides everything — go directly
        state <= EMERGENCY;
    end
    else if (maintenance && (state != EMERGENCY)) begin
        // Maintenance overrides normal flow (not emergency)
        state <= MAINTENANCE;
    end
    else begin
        state <= next_state;
    end
end

//  BLOCK 2 — Next-State Logic (combinational)
//  Determines next_state purely from current state + inputs.
//  No registers or side effects allowed here.

always @(*) begin
    // Default: stay in current state
    next_state = state;

    case (state)

        // ---- IDLE ----
        // Gate is closed, system is waiting for a card tap.
        IDLE: begin
            if (card_detected)
                next_state = CARD_DETECTED;
        end

        // ---- CARD_DETECTED ----
        // Brief acknowledgement state; move to validation immediately.
        CARD_DETECTED: begin
            next_state = VALIDATE;
        end

        // ---- VALIDATE ----
        // Wait for the ticket_valid signal from the backend/reader.
        VALIDATE: begin
            if (ticket_valid)
                next_state = OPEN_GATE;
            else if (!card_detected)
                // Card removed without valid result → invalid
                next_state = INVALID_TICKET;
            // If card still present but not yet valid, keep validating
        end

        // ---- OPEN_GATE ----
        // Command gate to open; move to wait-for-passenger immediately.
        OPEN_GATE: begin
            next_state = WAIT_FOR_PASSENGER;
        end

        // ---- WAIT_FOR_PASSENGER ----
        // Stay open until passenger crosses or timeout occurs.
        WAIT_FOR_PASSENGER: begin
            if (passenger_crossed)
                next_state = CLOSE_GATE;
            else if (timeout)
                next_state = CLOSE_GATE;  // Timed out — close anyway
        end

        // ---- CLOSE_GATE ----
        // Gate is commanded to close; return to IDLE next cycle.
        CLOSE_GATE: begin
            next_state = IDLE;
        end

        // ---- INVALID_TICKET ----
        // Keep gate closed, alarm fires briefly (handled in output block).
        // Return to IDLE after alarm countdown ends.
        INVALID_TICKET: begin
            if (alarm_cnt == 4'd0)
                next_state = IDLE;
        end

        // ---- EMERGENCY ----
        // Gate stays open. Exit only when emergency signal is deasserted.
        EMERGENCY: begin
            if (!emergency)
                next_state = IDLE;
        end

        // ---- MAINTENANCE ----
        // System locked. Exit when maintenance signal deasserted.
        MAINTENANCE: begin
            if (!maintenance)
                next_state = IDLE;
        end

        default: next_state = IDLE;

    endcase
end

//  BLOCK 3 — Output Logic (sequential, registered outputs)
//  Drives gate_open, alarm, display from current state.
//  Registered outputs prevent glitches on synthesized hardware.

always @(posedge clk) begin
    if (reset) begin
        gate_open    <= 1'b0;
        alarm        <= 1'b0;
        display      <= DISP_IDLE;
        count_en     <= 1'b0;
        alarm_cnt    <= 4'd0;
    end
    else begin
        // Default de-assertions each cycle (override below per state)
        count_en  <= 1'b0;
        alarm     <= 1'b0;

        case (state)

            IDLE: begin
                gate_open <= 1'b0;
                display   <= DISP_IDLE;
                alarm_cnt <= 4'd10;  // Pre-load alarm timer for next use
            end

            CARD_DETECTED: begin
                gate_open <= 1'b0;
                display   <= DISP_CARD;
            end

            VALIDATE: begin
                gate_open <= 1'b0;
                display   <= DISP_VALIDATING;
            end

            OPEN_GATE: begin
                gate_open <= 1'b1;
                display   <= DISP_OPEN;
            end

            WAIT_FOR_PASSENGER: begin
                gate_open <= 1'b1;
                display   <= DISP_WAIT;
                // Increment counter the cycle the passenger crosses
                if (passenger_crossed)
                    count_en <= 1'b1;
            end

            CLOSE_GATE: begin
                gate_open <= 1'b0;
                display   <= DISP_CLOSING;
            end

            INVALID_TICKET: begin
                gate_open <= 1'b0;
                display   <= DISP_INVALID;
                // Drive alarm and count down timer
                if (alarm_cnt != 4'd0) begin
                    alarm     <= 1'b1;
                    alarm_cnt <= alarm_cnt - 4'd1;
                end
            end

            EMERGENCY: begin
                gate_open <= 1'b1;   // Force gate open
                alarm     <= 1'b1;   // Alert staff
                display   <= DISP_EMERGENCY;
            end

            MAINTENANCE: begin
                gate_open <= 1'b0;   // Gate locked during maintenance
                alarm     <= 1'b0;
                display   <= DISP_MAINTENANCE;
            end

            default: begin
                gate_open <= 1'b0;
                display   <= DISP_IDLE;
            end

        endcase
    end
end

//  BLOCK 4 — Passenger Entry Counter (sequential)
//  Increments on the count_en pulse set in output logic above.
//  Wraps at 255 (natural 8-bit rollover).

always @(posedge clk) begin
    if (reset)
        entry_cnt_reg <= 8'd0;
    else if (count_en)
        entry_cnt_reg <= entry_cnt_reg + 8'd1;
end

endmodule

metro_ticket_gate_tb.v
module metro_ticket_gate_tb;

//  DUT Port Signals

reg        clk;
reg        reset;
reg        card_detected;
reg        ticket_valid;
reg        passenger_crossed;
reg        timeout;
reg        emergency;
reg        maintenance;

wire       gate_open;
wire       alarm;
wire [3:0] display;
wire [7:0] entry_count;

//  DUT Instantiation  (ports matched exactly — do not modify)

metro_ticket_gate dut (
    .clk              (clk),
    .reset            (reset),
    .card_detected    (card_detected),
    .ticket_valid     (ticket_valid),
    .passenger_crossed(passenger_crossed),
    .timeout          (timeout),
    .emergency        (emergency),
    .maintenance      (maintenance),
    .gate_open        (gate_open),
    .alarm            (alarm),
    .display          (display),
    .entry_count      (entry_count)
);

//  Clock Generation — 100 MHz  (period = 10 ns)

initial clk = 0;
always #5 clk = ~clk;

// Helper task: advance N rising edges and add a small read margin
task clk_step;
    input integer n;
    integer i;
    begin
        for (i = 0; i < n; i = i + 1)
            @(posedge clk);
        #1; // 1 ns after edge — outputs have settled
    end
endtask

//  Waveform Dump

initial begin
    $dumpfile("metro_ticket_gate.vcd");
    $dumpvars(0, metro_ticket_gate_tb);
end

//  Main Stimulus

initial begin
    // Initialise all inputs to safe (de-asserted) defaults
    reset            = 1;
    card_detected    = 0;
    ticket_valid     = 0;
    passenger_crossed= 0;
    timeout          = 0;
    emergency        = 0;
    maintenance      = 0;

    //  TEST 1 — System Reset
    //  Assert reset for 4 cycles; verify outputs are cleared.
   
    $display("\n[TEST 1] System Reset");
    clk_step(4);
    reset = 0;
    clk_step(1);
    $display("  reset deasserted | gate_open=%b alarm=%b display=%0h entry_count=%0d",
             gate_open, alarm, display, entry_count);

    //  TEST 2 — Valid Ticket Flow
    //  Tap card → validate → gate opens → passenger crosses →
    //  gate closes → entry_count increments.
   
    $display("\n[TEST 2] Valid Ticket — full happy path");

    // Tap card (IDLE → CARD_DETECTED)
    card_detected = 1;
    clk_step(1);   // CARD_DETECTED registered

    // CARD_DETECTED → VALIDATE (auto-transition, 1 cycle)
    clk_step(1);
    ticket_valid = 1;  // Backend confirms valid card

    // VALIDATE → OPEN_GATE (ticket_valid sampled)
    clk_step(1);
    $display("  OPEN_GATE state  | gate_open=%b  [expect 1]", gate_open);

    // OPEN_GATE → WAIT_FOR_PASSENGER (auto, 1 cycle)
    clk_step(1);

    // Passenger crosses
    passenger_crossed = 1;
    clk_step(1);   // WAIT_FOR_PASSENGER sees crossing → CLOSE_GATE
    passenger_crossed = 0;
    card_detected     = 0;
    ticket_valid      = 0;

    // CLOSE_GATE → IDLE (auto, 1 cycle)
    clk_step(2);
    $display("  After close      | gate_open=%b entry_count=%0d  [expect 0, 1]",
             gate_open, entry_count);

    //  TEST 3 — Invalid Ticket
    //  Tap card, ticket NOT valid, card removed → INVALID_TICKET
    //  state; alarm fires for 10 cycles; gate stays closed.
 
    $display("\n[TEST 3] Invalid Ticket — alarm check");

    card_detected = 1;
    clk_step(2);             // Through CARD_DETECTED → VALIDATE
    card_detected = 0;       // Remove card without ticket_valid → INVALID_TICKET
    clk_step(2);
    $display("  INVALID_TICKET   | gate_open=%b alarm=%b  [expect 0, 1]",
             gate_open, alarm);

    // Wait for alarm countdown (10 cycles)
    clk_step(12);
    $display("  Alarm expired    | gate_open=%b alarm=%b display=%0h  [expect 0, 0, 0]",
             gate_open, alarm, display);

    //  TEST 4 — Passenger Timeout
    //  Valid ticket, gate opens, passenger never crosses.
    //  Timeout signal fires → gate closes, count unchanged.
 
    $display("\n[TEST 4] Passenger Timeout — gate auto-close");

    card_detected = 1;
    clk_step(1);             // → CARD_DETECTED
    ticket_valid  = 1;
    clk_step(2);             // → VALIDATE → OPEN_GATE
    $display("  Gate opened      | gate_open=%b  [expect 1]", gate_open);

    clk_step(1);             // → WAIT_FOR_PASSENGER
    timeout = 1;             // Simulate timer expiry
    clk_step(1);             // → CLOSE_GATE
    timeout       = 0;
    card_detected = 0;
    ticket_valid  = 0;
    clk_step(2);             // → IDLE; output updates
    $display("  After timeout    | gate_open=%b entry_count=%0d  [expect 0, 1]",
             gate_open, entry_count);

    //  TEST 5 — Emergency Mode
    //  Assert emergency mid-IDLE; gate must open immediately.
    //  Deassert; system returns to IDLE.

    $display("\n[TEST 5] Emergency Mode — immediate gate override");

    emergency = 1;
    clk_step(1);             // State register overridden → EMERGENCY
    clk_step(1);             // Output block in EMERGENCY state
    $display("  EMERGENCY active | gate_open=%b alarm=%b  [expect 1, 1]",
             gate_open, alarm);

    emergency = 0;
    clk_step(2);             // FSM exits EMERGENCY → IDLE; outputs settle
    $display("  After emergency  | gate_open=%b alarm=%b  [expect 0, 0]",
             gate_open, alarm);

    //  TEST 6 — Maintenance Mode
    //  Assert maintenance; verify normal flow is blocked.
    //  Attempt to tap a card — system must ignore it.
    //  Deassert; normal operation resumes.

    $display("\n[TEST 6] Maintenance Mode — normal flow disabled");

    maintenance = 1;
    clk_step(2);             // State → MAINTENANCE; // Return to IDLE
    $display("  MAINTENANCE      | gate_open=%b alarm=%b display=%0h  [expect 0, 0, 8]",
             gate_open, alarm, display);

    // Try to tap a card — should be ignored while in MAINTENANCE
    card_detected = 1;
    ticket_valid  = 1;
    clk_step(3);
    $display("  Card tapped (MNT)| gate_open=%b  [expect 0 — gate stays shut]",
             gate_open);
    card_detected = 0;
    ticket_valid  = 0;

    maintenance = 0;
    clk_step(2);             // → IDLE
    $display("  After maintenance| gate_open=%b display=%0h  [expect 0, 0]",
             gate_open, display);
    //  Simulation Complete
    $display("\n[SIM] All test cases complete. entry_count = %0d\n", entry_count);
    $finish;
end

endmodule

metro_ticket_gate.vcd
$date
	Mon Jun 29 14:11:19 2026
$end
$version
	Icarus Verilog
$end
$timescale
	1s
$end
$scope module metro_ticket_gate_tb $end
$var wire 1 ! gate_open $end
$var wire 8 " entry_count [7:0] $end
$var wire 4 # display [3:0] $end
$var wire 1 $ alarm $end
$var reg 1 % card_detected $end
$var reg 1 & clk $end
$var reg 1 ' emergency $end
$var reg 1 ( maintenance $end
$var reg 1 ) passenger_crossed $end
$var reg 1 * reset $end
$var reg 1 + ticket_valid $end
$var reg 1 , timeout $end
$scope module dut $end
$var wire 1 % card_detected $end
$var wire 1 & clk $end
$var wire 1 ' emergency $end
$var wire 8 - entry_count [7:0] $end
$var wire 1 ( maintenance $end
$var wire 1 ) passenger_crossed $end
$var wire 1 * reset $end
$var wire 1 + ticket_valid $end
$var wire 1 , timeout $end
$var parameter 4 . CARD_DETECTED $end
$var parameter 4 / CLOSE_GATE $end
$var parameter 4 0 DISP_CARD $end
$var parameter 4 1 DISP_CLOSING $end
$var parameter 4 2 DISP_EMERGENCY $end
$var parameter 4 3 DISP_IDLE $end
$var parameter 4 4 DISP_INVALID $end
$var parameter 4 5 DISP_MAINTENANCE $end
$var parameter 4 6 DISP_OPEN $end
$var parameter 4 7 DISP_VALIDATING $end
$var parameter 4 8 DISP_WAIT $end
$var parameter 4 9 EMERGENCY $end
$var parameter 4 : IDLE $end
$var parameter 4 ; INVALID_TICKET $end
$var parameter 4 < MAINTENANCE $end
$var parameter 4 = OPEN_GATE $end
$var parameter 4 > VALIDATE $end
$var parameter 4 ? WAIT_FOR_PASSENGER $end
$var reg 1 $ alarm $end
$var reg 4 @ alarm_cnt [3:0] $end
$var reg 1 A count_en $end
$var reg 4 B display [3:0] $end
$var reg 8 C entry_cnt_reg [7:0] $end
$var reg 1 ! gate_open $end
$var reg 4 D next_state [3:0] $end
$var reg 4 E state [3:0] $end
$upscope $end
$scope task clk_step $end
$var integer 32 F i [31:0] $end
$var integer 32 G n [31:0] $end
$upscope $end
$upscope $end
$enddefinitions $end
$comment Show the parameter values. $end
$dumpall
b100 ?
b10 >
b11 =
b1000 <
b110 ;
b0 :
b111 9
b100 8
b10 7
b11 6
b1000 5
b110 4
b0 3
b111 2
b101 1
b1 0
b101 /
b1 .
$end
#0
$dumpvars
b100 G
b0 F
bx E
b0 D
bx C
bx B
xA
bx @
bx -
0,
0+
1*
0)
0(
0'
0&
0%
x$
bx #
bx "
x!
$end
#5
b0 E
b0 @
0A
b0 #
b0 B
0$
0!
b0 "
b0 -
b0 C
b1 F
1&
#10
0&
#15
b10 F
1&
#20
0&
#25
b11 F
1&
#30
0&
#35
b100 F
1&
#36
b0 F
b1 G
0*
#40
0&
#45
b1010 @
b1 F
1&
#46
b1 D
b0 F
1%
#50
0&
#55
b10 D
b1 E
b1 F
1&
#56
b0 F
#60
0&
#65
b10 E
b1 #
b1 B
b1 F
1&
#66
b11 D
b0 F
1+
#70
0&
#75
b100 D
b10 #
b10 B
b11 E
b1 F
1&
#76
b0 F
#80
0&
#85
b100 E
b11 #
b11 B
1!
b1 F
1&
#86
b101 D
b0 F
1)
#90
0&
#95
b0 D
1A
b100 #
b100 B
b101 E
b1 F
1&
#96
b0 D
b0 F
b10 G
0+
0%
0)
#100
0&
#105
b0 E
b101 #
b101 B
0!
0A
b1 "
b1 -
b1 C
b1 F
1&
#110
0&
#115
b0 #
b0 B
b10 F
1&
#116
b1 D
b0 F
1%
#120
0&
#125
b10 D
b1 E
b1 F
1&
#130
0&
#135
b1 #
b1 B
b10 E
b10 F
1&
#136
b110 D
b0 F
0%
#140
0&
#145
b110 E
b10 #
b10 B
b1 F
1&
#150
0&
#155
b1001 @
1$
b110 #
b110 B
b10 F
1&
#156
b0 F
b1100 G
#160
0&
#165
b1000 @
1$
b1 F
1&
#170
0&
#175
b111 @
1$
b10 F
1&
#180
0&
#185
b110 @
1$
b11 F
1&
#190
0&
#195
b101 @
1$
b100 F
1&
#200
0&
#205
b100 @
1$
b101 F
1&
#210
0&
#215
b11 @
1$
b110 F
1&
#220
0&
#225
b10 @
1$
b111 F
1&
#230
0&
#235
b1 @
1$
b1000 F
1&
#240
0&
#245
b0 D
b0 @
1$
b1001 F
1&
#250
0&
#255
0$
b0 E
b1010 F
1&
#260
0&
#265
b1010 @
b0 #
b0 B
b1011 F
1&
#270
0&
#275
b1100 F
1&
#276
b1 D
b0 F
b1 G
1%
#280
0&
#285
b10 D
b1 E
b1 F
1&
#286
b10 D
b0 F
b10 G
1+
#290
0&
#295
b11 D
b1 #
b1 B
b10 E
b1 F
1&
#300
0&
#305
b100 D
b11 E
b10 #
b10 B
b10 F
1&
#306
b0 F
b1 G
#310
0&
#315
b11 #
b11 B
1!
b100 E
b1 F
1&
#316
b101 D
b0 F
1,
#320
0&
#325
b0 D
b101 E
b100 #
b100 B
b1 F
1&
#326
b0 D
b0 F
b10 G
0+
0%
0,
#330
0&
#335
b101 #
b101 B
0!
b0 E
b1 F
1&
#340
0&
#345
b0 #
b0 B
b10 F
1&
#346
b0 F
b1 G
1'
#350
0&
#355
b111 D
b111 E
b1 F
1&
#356
b0 F
#360
0&
#365
b111 #
b111 B
1$
1!
b1 F
1&
#366
b0 D
b0 F
b10 G
0'
#370
0&
#375
1$
b0 E
b1 F
1&
#380
0&
#385
b0 #
b0 B
0!
0$
b10 F
1&
#386
b0 F
1(
#390
0&
#395
b1000 D
b1000 E
b1 F
1&
#400
0&
#405
b1000 #
b1000 B
b10 F
1&
#406
b0 F
b11 G
1+
1%
#410
0&
#415
b1 F
1&
#420
0&
#425
b10 F
1&
#430
0&
#435
b11 F
1&
#436
b0 D
b0 F
b10 G
0(
0+
0%
#440
0&
#445
b0 E
b1 F
1&
#450
0&
#455
b0 #
b0 B
b10 F
1&
